coordinate_projector/__init__.py
coordinate_projector/datetime_parser.py
coordinate_projector/projector.py
coordinate_projector/py.typed
coordinate_projector-0.0.15.dist-info/METADATA
coordinate_projector-0.0.15.dist-info/WHEEL
coordinate_projector-0.0.15.dist-info/licenses/LICENSE
coordinate_projector-0.0.15.dist-info/RECORD
