Metadata-Version: 2.4
Name: coordinate-projector
Version: 0.0.15
Summary: Project points from one projection to another using pyproj
Project-URL: Homepage, https://github.com/norwegian-geotechnical-institute/coordinate-projector
Project-URL: Repository, https://github.com/norwegian-geotechnical-institute/coordinate-projector
Author: Helge Smebye
Author-email: Jostein Leira <jostein@leira.net>
Maintainer-email: Jostein Leira <jostein@leira.net>
License-Expression: MIT
License-File: LICENSE
Classifier: Development Status :: 5 - Production/Stable
Classifier: Operating System :: OS Independent
Classifier: Programming Language :: Python :: 3
Classifier: Topic :: Scientific/Engineering :: GIS
Requires-Python: <4,>=3.11
Requires-Dist: pyproj<4,>=3.6.1
Requires-Dist: python-dateutil<3,>=2.8.2
Requires-Dist: types-python-dateutil<3,>=2.8.19
Requires-Dist: tzfpy[tzdata]>=1.0.0
